{
  "metadata": {
    "title": "Arquitectura Objetivo AWS — Modernización Sistema Bancario Legacy",
    "system": "payments-core / BankDemo",
    "version": "2.0",
    "generated_at": "2026-03-20",
    "alignment": "AWS Financial Services Reference Architecture",
    "regulatory_frameworks": ["PCI-DSS v4.0", "SOX", "GDPR", "Basel III", "NIST CSF"],
    "region": "us-east-2",
    "classification": "Confidential — Technical Use Only"
  },
  "current_state": {
    "cloud_readiness_score": 38,
    "data_quality_score": 76,
    "security_risk_score": 78,
    "compliance_risk_score": 74,
    "pci_readiness_score": 56,
    "encryption_coverage_score": 35,
    "pii_exposure_score": 72,
    "auditability_score": 87,
    "critical_findings": [
      "PII stored in plaintext (customer_name, customer_email)",
      "No authentication layer on payments-core",
      "Hardcoded database credentials",
      "No audit trail (CloudTrail equivalent)",
      "No data lineage tracking",
      "No encryption at rest or in transit",
      "SQL Server on-premises without HA"
    ]
  },
  "target_state": {
    "cloud_readiness_score": 85,
    "data_quality_score": 92,
    "security_risk_score": 25,
    "compliance_risk_score": 20,
    "pci_readiness_score": 90,
    "encryption_coverage_score": 98,
    "pii_exposure_score": 10,
    "auditability_score": 98
  },
  "architecture_layers": [
    {
      "layer": "governance_and_control",
      "name": "Gobernanza y Control",
      "services": ["AWS Control Tower", "AWS Security Hub", "AWS Audit Manager", "AWS Config"]
    },
    {
      "layer": "identity_and_access",
      "name": "Identidad y Acceso",
      "services": ["AWS IAM", "AWS Secrets Manager", "Amazon Cognito"]
    },
    {
      "layer": "network_and_perimeter",
      "name": "Red y Perímetro",
      "services": ["Amazon VPC", "AWS WAF", "Application Load Balancer", "VPC Endpoints"]
    },
    {
      "layer": "compute_and_application",
      "name": "Cómputo y Aplicación",
      "services": ["Amazon EKS", "AWS WAF", "Application Load Balancer"]
    },
    {
      "layer": "data",
      "name": "Datos",
      "services": ["Amazon Aurora PostgreSQL", "Amazon S3", "AWS KMS", "Amazon Macie"]
    },
    {
      "layer": "analytics_and_governance",
      "name": "Analytics y Gobernanza de Datos",
      "services": ["AWS Glue", "AWS Lake Formation", "Amazon Athena", "Amazon QuickSight"]
    },
    {
      "layer": "audit_and_observability",
      "name": "Auditoría y Observabilidad",
      "services": ["AWS CloudTrail", "Amazon CloudWatch", "Amazon EventBridge", "Amazon SNS"]
    }
  ],
  "network_architecture": {
    "vpc_cidr": "10.0.0.0/16",
    "region": "us-east-2",
    "availability_zones": ["us-east-2a", "us-east-2b"],
    "subnets": {
      "public": [
        {"name": "public-az-a", "cidr": "10.0.1.0/24", "az": "us-east-2a", "purpose": "ALB, WAF"},
        {"name": "public-az-b", "cidr": "10.0.2.0/24", "az": "us-east-2b", "purpose": "ALB, WAF (HA)"}
      ],
      "private_app": [
        {"name": "app-az-a", "cidr": "10.0.10.0/24", "az": "us-east-2a", "purpose": "EKS nodes, payments-core"},
        {"name": "app-az-b", "cidr": "10.0.11.0/24", "az": "us-east-2b", "purpose": "EKS nodes (HA)"}
      ],
      "private_data": [
        {"name": "data-az-a", "cidr": "10.0.20.0/24", "az": "us-east-2a", "purpose": "Aurora primary"},
        {"name": "data-az-b", "cidr": "10.0.21.0/24", "az": "us-east-2b", "purpose": "Aurora replica (Multi-AZ)"}
      ]
    },
    "vpc_endpoints": [
      {"service": "com.amazonaws.us-east-2.s3", "type": "Gateway"},
      {"service": "com.amazonaws.us-east-2.kms", "type": "Interface"},
      {"service": "com.amazonaws.us-east-2.secretsmanager", "type": "Interface"},
      {"service": "com.amazonaws.us-east-2.athena", "type": "Interface"},
      {"service": "com.amazonaws.us-east-2.glue", "type": "Interface"}
    ],
    "security_groups": {
      "alb-sg": {"inbound": ["443/tcp from 0.0.0.0/0"], "outbound": ["8080/tcp to app-sg"]},
      "app-sg": {"inbound": ["8080/tcp from alb-sg"], "outbound": ["5432/tcp to data-sg", "443/tcp to vpc-endpoints"]},
      "data-sg": {"inbound": ["5432/tcp from app-sg"], "outbound": []}
    }
  },
  "banking_specific_controls": {
    "pci_dss_v4": {
      "req_1_network_security": {
        "control": "VPC con subnets privadas + Security Groups restrictivos",
        "implementation": "No acceso directo a base de datos desde internet; WAF en perímetro",
        "status": "required"
      },
      "req_3_data_protection": {
        "control": "KMS CMK para todos los datos de tarjetas y PII",
        "implementation": "SSE-KMS en S3 + cifrado en Aurora + TLS en tránsito",
        "status": "required"
      },
      "req_7_access_control": {
        "control": "IAM roles de mínimo privilegio + Lake Formation RBAC",
        "implementation": "Column-level security en tablas con PII; roles por función",
        "status": "required"
      },
      "req_8_authentication": {
        "control": "MFA obligatorio + IAM database authentication",
        "implementation": "Sin contraseñas hardcodeadas; Secrets Manager para rotación",
        "status": "required"
      },
      "req_10_logging": {
        "control": "CloudTrail multi-región + VPC Flow Logs + Aurora audit logs",
        "implementation": "Logs inmutables con Object Lock COMPLIANCE; retención 7 años",
        "status": "required"
      }
    },
    "sox_controls": {
      "section_302_404": {
        "control": "Audit Manager con assessment SOX activo",
        "implementation": "Evidencia automática de controles; mapeo a recursos AWS",
        "status": "required"
      },
      "data_lineage": {
        "control": "Glue Data Catalog + Lake Formation lineage",
        "implementation": "Trazabilidad completa de transformaciones de datos financieros",
        "status": "required"
      },
      "segregation_of_duties": {
        "control": "Control Tower SCPs + IAM roles separados por función",
        "implementation": "Entornos prod/dev separados; aprobación dual para break-glass",
        "status": "required"
      }
    },
    "gdpr_controls": {
      "art_30_records": {
        "control": "Macie + Lake Formation para inventario de datos personales",
        "implementation": "Detección automática diaria de PII en todos los buckets",
        "status": "required"
      },
      "art_32_security": {
        "control": "KMS CMK + TLS 1.3 + column masking en Lake Formation",
        "implementation": "Cifrado end-to-end de datos personales",
        "status": "required"
      },
      "data_minimization": {
        "control": "Lake Formation column-level security por rol",
        "implementation": "Analistas no acceden a customer_name ni customer_email",
        "status": "required"
      }
    },
    "basel_iii_bcbs239": {
      "data_aggregation": {
        "control": "Glue ETL + Athena para agregación de datos de riesgo",
        "implementation": "Pipeline automatizado con linaje completo",
        "status": "required"
      },
      "risk_reporting": {
        "control": "QuickSight dashboards + Athena named queries",
        "implementation": "Reportes de riesgo reproducibles y auditables",
        "status": "required"
      }
    }
  },
  "disaster_recovery": {
    "rpo_rto_targets": [
      {"component": "Aurora PostgreSQL", "rpo_hours": 1, "rto_hours": 4, "strategy": "Multi-AZ automático + backups 35 días"},
      {"component": "S3 Data Lake", "rpo_hours": 0, "rto_hours": 1, "strategy": "Versioning + Cross-region replication"},
      {"component": "EKS payments-core", "rpo_minutes": 15, "rto_hours": 2, "strategy": "Multi-AZ node groups + HPA"},
      {"component": "CloudTrail logs", "rpo_hours": 0, "rto_hours": 0, "strategy": "Object Lock COMPLIANCE — inmutable"},
      {"component": "Secrets Manager", "rpo_hours": 0, "rto_hours": 1, "strategy": "Cross-region replication"}
    ],
    "backup_strategy": {
      "aurora": {"automated_backups_days": 35, "manual_snapshots": "weekly", "cross_region": true},
      "s3": {"versioning": true, "cross_region_replication": true, "destination_region": "us-west-2"},
      "cloudtrail": {"object_lock": "COMPLIANCE", "retention_years": 7}
    }
  },
  "compliance_mapping": {
    "PCI-DSS v4.0": {
      "req_1": "VPC + Security Groups + WAF",
      "req_2": "Control Tower SCPs + Config Rules",
      "req_3": "KMS CMK + SSE-KMS + Macie",
      "req_4": "TLS 1.3 en ALB + Aurora + VPC Endpoints",
      "req_7": "IAM roles + Lake Formation RBAC",
      "req_8": "IAM + MFA + Secrets Manager",
      "req_10": "CloudTrail + VPC Flow Logs + CloudWatch",
      "req_11": "Security Hub + GuardDuty + Inspector",
      "req_12": "Audit Manager + Config + Control Tower"
    },
    "SOX": {
      "section_302": "Audit Manager assessment SOX",
      "section_404": "Config Rules + CloudTrail + Audit Manager evidence",
      "data_lineage": "Glue Data Catalog + Lake Formation",
      "segregation": "Control Tower accounts + IAM roles"
    },
    "GDPR": {
      "art_5_principles": "Lake Formation data minimization",
      "art_25_privacy_by_design": "KMS + column masking por defecto",
      "art_30_records": "Macie inventory + Glue Catalog",
      "art_32_security": "KMS + TLS + Security Hub",
      "art_33_breach_notification": "GuardDuty + EventBridge + SNS"
    },
    "Basel III BCBS 239": {
      "data_aggregation": "Glue ETL + Athena",
      "risk_reporting": "QuickSight + Athena named queries",
      "data_quality": "DQ Engine + Glue Data Quality",
      "auditability": "CloudTrail + Audit Manager"
    },
    "NIST CSF": {
      "identify": "Security Hub + Config + Macie",
      "protect": "KMS + IAM + WAF + Lake Formation",
      "detect": "GuardDuty + Security Hub + CloudTrail",
      "respond": "EventBridge + Lambda + SNS",
      "recover": "Aurora Multi-AZ + S3 versioning + DR plan"
    }
  },
  "services": [
    {
      "id": "control-tower",
      "name": "AWS Control Tower",
      "layer": "governance_and_control",
      "risk_resolved": "Configuraciones inseguras por defecto; falta de gobernanza multi-cuenta",
      "regulatory_coverage": ["PCI-DSS Req. 1", "PCI-DSS Req. 2", "SOX — Segregación de entornos"],
      "account_structure": {
        "management": "Cuenta raíz de Control Tower",
        "security": "Security Hub, GuardDuty, Macie centralizados",
        "log-archive": "CloudTrail logs con Object Lock",
        "payments-prod": "Workload de producción",
        "payments-dev": "Entorno de desarrollo y pruebas"
      },
      "critical_guardrails": [
        "Disallow public S3 buckets",
        "Require CloudTrail in all regions",
        "Disallow root account usage",
        "Require MFA for IAM users",
        "Disallow creation of access keys for root"
      ]
    },
    {
      "id": "security-hub",
      "name": "AWS Security Hub",
      "layer": "governance_and_control",
      "risk_resolved": "Visibilidad fragmentada de postura de seguridad",
      "regulatory_coverage": ["PCI-DSS Req. 11", "NIST CSF — Identify/Detect"],
      "enabled_standards": ["PCI-DSS v3.2.1", "CIS AWS Foundations Benchmark v1.4", "AWS Foundational Security Best Practices"],
      "integrations": ["Amazon GuardDuty", "Amazon Macie", "AWS Config", "AWS Inspector", "AWS Firewall Manager"]
    },
    {
      "id": "audit-manager",
      "name": "AWS Audit Manager",
      "layer": "governance_and_control",
      "risk_resolved": "Proceso manual de auditoría propenso a errores",
      "regulatory_coverage": ["SOX Sección 302/404", "PCI-DSS — Evidencia de controles", "SOC 2"],
      "active_assessments": ["PCI-DSS", "SOX"],
      "evidence_retention_years": 7,
      "evidence_storage": "s3://log-archive/audit-manager/"
    },
    {
      "id": "aws-config",
      "name": "AWS Config",
      "layer": "governance_and_control",
      "risk_resolved": "Drift de configuración no detectado",
      "regulatory_coverage": ["PCI-DSS Req. 2", "PCI-DSS Req. 10", "Basel III — Riesgo operacional"],
      "critical_rules": [
        "rds-storage-encrypted",
        "s3-bucket-server-side-encryption-enabled",
        "s3-bucket-ssl-requests-only",
        "cloudtrail-enabled",
        "iam-root-access-key-check",
        "iam-no-inline-policy",
        "restricted-ssh",
        "vpc-flow-logs-enabled",
        "kms-cmk-not-scheduled-for-deletion"
      ]
    },
    {
      "id": "cloudtrail",
      "name": "AWS CloudTrail",
      "layer": "audit_and_observability",
      "risk_resolved": "Ausencia de audit trail — hallazgo crítico con 130 findings de compliance",
      "regulatory_coverage": ["SOX Sección 404", "PCI-DSS Req. 10", "Basel III BCBS 239"],
      "configuration": {
        "multi_region": true,
        "log_file_validation": true,
        "s3_bucket": "s3://log-archive/cloudtrail/",
        "object_lock": true,
        "object_lock_mode": "COMPLIANCE",
        "retention_years": 7,
        "cloudwatch_logs_integration": true,
        "kms_encryption": "cloudtrail-cmk"
      }
    },
    {
      "id": "kms",
      "name": "AWS KMS",
      "layer": "data",
      "risk_resolved": "PII Exposure Score 72/100; customer_name y customer_email en texto plano",
      "regulatory_coverage": ["PCI-DSS Req. 3", "GDPR Art. 32", "NIST 800-53 SC-28"],
      "cmk_structure": {
        "payments-data-cmk": "Aurora + S3 datos de pagos",
        "audit-logs-cmk": "CloudTrail + Audit Manager evidence",
        "secrets-cmk": "Secrets Manager",
        "glue-catalog-cmk": "Glue Data Catalog + Lake Formation"
      },
      "key_rotation": true,
      "key_rotation_period_days": 365
    },
    {
      "id": "macie",
      "name": "Amazon Macie",
      "layer": "data",
      "risk_resolved": "PII en texto plano en clean/ y errors/",
      "regulatory_coverage": ["GDPR Art. 30", "PCI-DSS Req. 3.2"],
      "configuration": {
        "enabled_buckets": ["bankdemo"],
        "job_frequency": "DAILY",
        "findings_destination": "EventBridge → SNS → compliance-team",
        "managed_data_identifiers": ["CREDIT_CARD_NUMBER", "EMAIL_ADDRESS", "NAME", "BANK_ACCOUNT_NUMBER"]
      }
    },
    {
      "id": "lake-formation",
      "name": "AWS Lake Formation",
      "layer": "analytics_and_governance",
      "risk_resolved": "Acceso sin restricciones a datos PII",
      "regulatory_coverage": ["PCI-DSS Req. 7", "GDPR — Minimización de datos", "SOX — Segregación de funciones"],
      "role_permissions": {
        "analyst-role": {
          "tables": ["payments_clean"],
          "excluded_columns": ["customer_name", "customer_email"],
          "row_filter": "none"
        },
        "compliance-role": {
          "tables": ["payments_clean", "payments_errors", "compliance_findings"],
          "column_masking": ["customer_email"],
          "row_filter": "none"
        },
        "audit-role": {
          "tables": ["ALL"],
          "column_masking": "none",
          "row_filter": "none",
          "access_logged": true
        }
      }
    },
    {
      "id": "glue",
      "name": "AWS Glue",
      "layer": "analytics_and_governance",
      "risk_resolved": "Ausencia de linaje de datos — hallazgo SOX/Basel III",
      "regulatory_coverage": ["SOX — Trazabilidad de datos financieros", "Basel III BCBS 239"],
      "components": {
        "crawlers": ["payments-raw-crawler", "payments-clean-crawler", "payments-errors-crawler"],
        "jobs": ["raw-to-clean-etl", "compliance-enrichment-job"],
        "catalog_database": "bankdemo_db",
        "catalog_tables": ["payments_raw", "payments_clean", "payments_errors", "compliance_findings"]
      }
    },
    {
      "id": "athena",
      "name": "Amazon Athena",
      "layer": "analytics_and_governance",
      "risk_resolved": "Imposibilidad de consultar datos históricos para auditorías",
      "regulatory_coverage": ["SOX — Consulta de registros financieros históricos", "PCI-DSS Req. 10.7"],
      "workgroups": {
        "primary": "Pipeline operacional",
        "audit": "Consultas de auditoría — output cifrado con KMS"
      },
      "named_queries": [
        "payments-last-24h-by-status",
        "high-value-transactions-audit",
        "pii-access-cloudtrail-query",
        "compliance-findings-summary"
      ]
    },
    {
      "id": "s3",
      "name": "Amazon S3",
      "layer": "data",
      "risk_resolved": "Datos de pagos sin cifrar; sin segregación por sensibilidad",
      "regulatory_coverage": ["PCI-DSS Req. 3", "PCI-DSS Req. 9", "SOX — Retención 7 años"],
      "zones": {
        "raw":    {"path": "bankdemo/raw/",    "encryption": "SSE-KMS", "versioning": true},
        "clean":  {"path": "bankdemo/clean/",  "encryption": "SSE-KMS", "versioning": true},
        "errors": {"path": "bankdemo/errors/", "encryption": "SSE-KMS", "versioning": true},
        "output": {"path": "bankdemo/output/", "encryption": "SSE-KMS", "versioning": true},
        "audit":  {"path": "bankdemo/audit/",  "encryption": "SSE-KMS", "object_lock": true, "object_lock_mode": "COMPLIANCE", "retention_years": 7}
      }
    },
    {
      "id": "aurora",
      "name": "Amazon Aurora PostgreSQL",
      "layer": "data",
      "risk_resolved": "SQL Server on-premises sin cifrado, sin HA, con credenciales hardcodeadas",
      "regulatory_coverage": ["PCI-DSS Req. 3", "PCI-DSS Req. 6", "SOX — Disponibilidad de sistemas financieros"],
      "configuration": {
        "engine": "aurora-postgresql",
        "instance_class": "db.r6g.large",
        "multi_az": true,
        "region": "us-east-2",
        "encryption": true,
        "kms_key": "payments-data-cmk",
        "iam_database_authentication": true,
        "deletion_protection": true,
        "backup_retention_days": 35,
        "performance_insights": true,
        "enhanced_monitoring": true
      }
    },
    {
      "id": "iam",
      "name": "AWS IAM",
      "layer": "identity_and_access",
      "risk_resolved": "Acceso sin autenticación al sistema de pagos; sin segregación de roles",
      "regulatory_coverage": ["PCI-DSS Req. 7", "PCI-DSS Req. 8", "SOX — Segregación de funciones"],
      "roles": {
        "payments-app-role":      ["Aurora read/write", "S3 raw write", "Secrets Manager read"],
        "dq-engine-role":         ["S3 raw read", "S3 clean+errors write", "S3 output write"],
        "compliance-engine-role": ["S3 clean+errors+output read", "S3 output/compliance write"],
        "audit-read-role":        ["S3 output read", "Athena query", "CloudTrail read"],
        "admin-break-glass-role": ["Full access — MFA + dual approval required"]
      }
    }
  ],
  "implementation_phases": [
    {
      "phase": 1,
      "name": "Fundamentos de Seguridad",
      "duration_weeks": "1-4",
      "priority": "CRITICAL",
      "actions": [
        "Habilitar CloudTrail multi-región",
        "Cifrar buckets S3 con KMS CMK",
        "Migrar credenciales a Secrets Manager",
        "Habilitar Security Hub con estándar PCI-DSS",
        "Configurar AWS Config con reglas críticas"
      ]
    },
    {
      "phase": 2,
      "name": "Gobernanza y Control",
      "duration_weeks": "5-8",
      "priority": "HIGH",
      "actions": [
        "Desplegar Control Tower Landing Zone",
        "Configurar Audit Manager (PCI + SOX)",
        "Habilitar Macie en buckets de pagos",
        "Implementar Lake Formation RBAC",
        "Configurar Glue Catalog + Crawlers"
      ]
    },
    {
      "phase": 3,
      "name": "Migración de Datos",
      "duration_weeks": "9-16",
      "priority": "HIGH",
      "actions": [
        "Provisionar Aurora PostgreSQL Multi-AZ",
        "Migrar payments_raw con AWS DMS",
        "Validar DQ Score post-migración",
        "Ejecutar compliance assessment en Aurora",
        "Activar IAM database authentication"
      ]
    },
    {
      "phase": 4,
      "name": "Operaciones y Optimización",
      "duration_weeks": "17-24",
      "priority": "MEDIUM",
      "actions": [
        "Dashboards ejecutivos en QuickSight",
        "Automatizar remediación con Config Rules + Lambda",
        "Implementar GuardDuty threat detection",
        "Prueba de auditoría PCI-DSS completa",
        "Documentar arquitectura final para SOX"
      ]
    }
  ],
  "estimated_monthly_cost_usd": {
    "aurora_postgresql_multi_az": 350,
    "amazon_eks": 140,
    "aws_glue": 130,
    "aws_config": 45,
    "aws_security_hub": 30,
    "aws_audit_manager": 20,
    "aws_cloudtrail": 15,
    "amazon_athena": 12,
    "aws_kms": 8,
    "amazon_macie": 5,
    "amazon_s3": 25,
    "aws_secrets_manager": 3,
    "total_estimated": 783
  }
}
